escape_nt_command_line_argument.py
escape_nt_command_line_argument-0.1.0a0.dist-info/licenses/LICENSE
escape_nt_command_line_argument-0.1.0a0.dist-info/METADATA
escape_nt_command_line_argument-0.1.0a0.dist-info/WHEEL
escape_nt_command_line_argument-0.1.0a0.dist-info/top_level.txt
escape_nt_command_line_argument-0.1.0a0.dist-info/RECORD
