Metadata-Version: 2.4
Name: escape-nt-command-line-argument
Version: 0.1.0a0
Summary: A readable, reliable, reviewable solution for escaping NT command-line arguments with explicit, single-pass state machine logic.
Author-email: Jifeng Wu <jifengwu2k@gmail.com>
License-Expression: MIT
Project-URL: Homepage, https://github.com/jifengwu2k/escape-nt-command-line-argument
Project-URL: Bug Tracker, https://github.com/jifengwu2k/escape-nt-command-line-argument/issues
Classifier: Programming Language :: Python :: 2
Classifier: Programming Language :: Python :: 3
Classifier: Operating System :: OS Independent
Requires-Python: >=2
License-File: LICENSE
Requires-Dist: cowlist
Requires-Dist: typing; python_version < "3.5"
Dynamic: license-file
